Perceptron/__init__.py
Perceptron/perceptron.py
Perceptron_pypi_monika0710-0.0.2.dist-info/LICENSE
Perceptron_pypi_monika0710-0.0.2.dist-info/METADATA
Perceptron_pypi_monika0710-0.0.2.dist-info/WHEEL
Perceptron_pypi_monika0710-0.0.2.dist-info/top_level.txt
Perceptron_pypi_monika0710-0.0.2.dist-info/RECORD
