Metadata-Version: 2.1
Name: Perceptron-pypi-monika0710
Version: 0.0.2
Summary: It's an implementation of Perceptron
Home-page: https://github.com/monika0710/Perceptron_pypi
Author: monika0710
Author-email: monikabhargav11@gmail.com
License: UNKNOWN
Project-URL: Bug Tracker, https://github.com/monika0710/Perceptron_pypi/issues
Platform: UNKNOWN
Classifier: Programming Language :: Python :: 3
Classifier: License :: OSI Approved :: MIT License
Classifier: Operating System :: OS Independent
Requires-Python: >=3.7
License-File: LICENSE
Requires-Dist: numpy
Requires-Dist: tqdm
Requires-Dist: logging
